mcp_server_demo/__init__.py
mcp_server_demo/__main__.py
mcp_server_demo/mcp_server_demo.py
mcp_server_demo-0.4.1.dist-info/METADATA
mcp_server_demo-0.4.1.dist-info/WHEEL
mcp_server_demo-0.4.1.dist-info/entry_points.txt
mcp_server_demo-0.4.1.dist-info/RECORD
