Metadata-Version: 2.4
Name: mcp-server-demo
Version: 0.4.1
Summary: Add your description here
Author-email: Seemant Tripathi <tripathiseemant766@gmail.com>
Requires-Python: >=3.11
Requires-Dist: build>=1.2.2.post1
Requires-Dist: twine>=6.1.0
